pybads/__init__.py
pybads/__main__.py
pybads/_version.py
pybads/function_examples.py
pybads/acquisition_functions/__init__.py
pybads/acquisition_functions/acq_fcn_lcb.py
pybads/bads/README.md
pybads/bads/__init__.py
pybads/bads/bads.py
pybads/bads/bads_dump.py
pybads/bads/gaussian_process_train.py
pybads/bads/optimize_result.py
pybads/bads/options.py
pybads/bads/option_configs/__init__.py
pybads/bads/option_configs/advanced_bads_options.ini
pybads/bads/option_configs/basic_bads_options.ini
pybads/bads/option_configs/options_confs.py
pybads/bads/option_configs/test_options.ini
pybads/bads/option_configs/test_options2.ini
pybads/decorators/README.md
pybads/decorators/__init__.py
pybads/decorators/handle_0D_1D_input.py
pybads/examples/pybads_example_1_basic_usage.ipynb
pybads/examples/pybads_example_2_nonbox_constraints.ipynb
pybads/examples/pybads_example_3_noisy_objective.ipynb
pybads/examples/pybads_example_4_user_provided_noise.ipynb
pybads/examples/pybads_example_5_extended_usage.ipynb
pybads/examples/scripts/pybads_example_1_basic_usage.py
pybads/examples/scripts/pybads_example_2_nonbox_constraints.py
pybads/examples/scripts/pybads_example_3_noisy_objective.py
pybads/examples/scripts/pybads_example_4_user_provided_noise.py
pybads/examples/scripts/pybads_example_5_extended_usage.py
pybads/function_logger/__init__.py
pybads/function_logger/constraints_check.py
pybads/function_logger/function_logger.py
pybads/init_functions/__init__.py
pybads/init_functions/init_sobol.py
pybads/poll/__init__.py
pybads/poll/poll_mads_2n.py
pybads/search/__init__.py
pybads/search/es_search.py
pybads/search/grid_functions.py
pybads/search/search_hedge.py
pybads/stats/README.md
pybads/stats/__init__.py
pybads/stats/get_hpd.py
pybads/stats/kde1d.py
pybads/stats/kldiv_mvn.py
pybads/testing/__init__.py
pybads/testing/run_tests.py
pybads/testing/bads/X.dat
pybads/testing/bads/__init__.py
pybads/testing/bads/dF.dat
pybads/testing/bads/dF_gplogjoint.dat
pybads/testing/bads/hyp.dat
pybads-1.0.6.dist-info/licenses/LICENSE
pybads-1.0.6.dist-info/METADATA
pybads-1.0.6.dist-info/WHEEL
pybads-1.0.6.dist-info/top_level.txt
pybads-1.0.6.dist-info/RECORD
