Metadata-Version: 2.4
Name: PyBADS
Version: 1.0.6
Summary: Bayesian Adaptive Direct Search in Python.
License: BSD 3-Clause License
Requires-Python: >=3.9
License-File: LICENSE
Requires-Dist: gpyreg>=0.1.0
Requires-Dist: matplotlib>=3.5.1
Requires-Dist: numpy>=1.22.1
Requires-Dist: pytest>=6.2.5
Requires-Dist: pytest-mock>=3.6.1
Requires-Dist: pytest-rerunfailures>=10.2
Requires-Dist: scipy>=1.7.3
Provides-Extra: dev
Requires-Dist: imageio>=2.13.5; extra == "dev"
Requires-Dist: corner>=2.2.1; extra == "dev"
Requires-Dist: dill>=0.3.5.1; extra == "dev"
Requires-Dist: myst_nb>=0.13.1; extra == "dev"
Requires-Dist: numpydoc>=1.2.1; extra == "dev"
Requires-Dist: pylint>=2.15.5; extra == "dev"
Requires-Dist: pytest-cov>=4.0.0; extra == "dev"
Requires-Dist: sphinx>=4.3.2; extra == "dev"
Requires-Dist: sphinx-book-theme>=0.2.0; extra == "dev"
Requires-Dist: build>=0.9.0; extra == "dev"
Dynamic: license-file
